pygazpar/__init__.py
pygazpar/__main__.py
pygazpar/api_client.py
pygazpar/client.py
pygazpar/datasource.py
pygazpar/enum.py
pygazpar/excelparser.py
pygazpar/jsonparser.py
pygazpar/resources/daily_data_sample.json
pygazpar/resources/hourly_data_sample.json
pygazpar/resources/monthly_data_sample.json
pygazpar/resources/weekly_data_sample.json
pygazpar/resources/yearly_data_sample.json
pygazpar/version.py
pygazpar-1.3.1.dist-info/LICENSE
pygazpar-1.3.1.dist-info/METADATA
pygazpar-1.3.1.dist-info/WHEEL
pygazpar-1.3.1.dist-info/RECORD
