Metadata-Version: 2.3
Name: pygazpar
Version: 1.3.1
Summary: Python library to download gas consumption from a GrDF (French Gas Company) account
License: MIT License
Author: Stéphane Senart
Requires-Python: >=3.10
Classifier: Programming Language :: Python :: 3.10
Classifier: Programming Language :: Python :: 3.11
Classifier: Programming Language :: Python :: 3.12
Classifier: Programming Language :: Python :: 3.13
Requires-Dist: openpyxl (>=3.1.5,<4.0.0)
Requires-Dist: pandas (>=2.1.4,<3.0.0)
Requires-Dist: requests (>=2.32.3,<3.0.0)
